[
    {
        "title": "Onramp",
        "subtitle": "Introduktionskurs",
        "date": "13, 16 & 17 maj"
    },
    {
        "title": "CrossFit Kids avslutning",
        "subtitle": "",
        "date": "22-23 maj"
    },
    {
        "title": "Test week",
        "subtitle": "",
        "date": "8-13 juni"
    },
    {
        "title": "Yoga",
        "subtitle": "",
        "date": "7 juni"
    },
    {
        "title": "Onramp",
        "subtitle": "Introduktionskurs",
        "date": "10, 13 & 14 juni"
    }
]